[
    {
        "dir": "http://www.jb51.net/article/98813.htm",
        "title": "nodejs连接mongodb数据库实现增删改查"
    },
    {
        "dir": "http://www.jb51.net/article/98638.htm",
        "title": "Node.js开发教程之基于OnceIO框架实现文件上传和验证功能"
    },
    {
        "dir": "http://www.jb51.net/article/98621.htm",
        "title": "Nodejs 搭建简单的Web服务器详解及实例"
    },
    {
        "dir": "http://www.jb51.net/article/98501.htm",
        "title": "基于Node.js + WebSocket打造即时聊天程序嗨聊"
    },
    {
        "dir": "http://www.jb51.net/article/98305.htm",
        "title": "node.js中的事件处理机制详解"
    },
    {
        "dir": "http://www.jb51.net/article/98300.htm",
        "title": "使用node.js中的Buffer类处理二进制数据的方法"
    },
    {
        "dir": "http://www.jb51.net/article/98200.htm",
        "title": "详解Node.js：events事件模块"
    },
    {
        "dir": "http://www.jb51.net/article/98153.htm",
        "title": "node.js版本管理工具n无效的原理和解决方法"
    },
    {
        "dir": "http://www.jb51.net/article/98087.htm",
        "title": "浅析Node.js：DNS模块的使用"
    },
    {
        "dir": "http://www.jb51.net/article/97853.htm",
        "title": "全面解析node 表单的图片上传"
    },
    {
        "dir": "http://www.jb51.net/article/97840.htm",
        "title": "Nodejs下用submit提交表单提示cannot post错误的解决方法"
    },
    {
        "dir": "http://www.jb51.net/article/97814.htm",
        "title": "Nodejs进阶：核心模块net入门学习与实例讲解"
    },
    {
        "dir": "http://www.jb51.net/article/97804.htm",
        "title": "Nodejs进阶：基于express+multer的文件上传实例"
    },
    {
        "dir": "http://www.jb51.net/article/97797.htm",
        "title": "Nodejs进阶：如何将图片转成datauri嵌入到网页中去实例"
    },
    {
        "dir": "http://www.jb51.net/article/97783.htm",
        "title": "Node.js测试中的Mock文件系统详解"
    },
    {
        "dir": "http://www.jb51.net/article/97738.htm",
        "title": "node+experss实现爬取电影天堂爬虫"
    },
    {
        "dir": "http://www.jb51.net/article/97659.htm",
        "title": "Node.js 实现简单小说爬虫实例"
    },
    {
        "dir": "http://www.jb51.net/article/97500.htm",
        "title": "Nodejs下DNS缓存问题浅析"
    },
    {
        "dir": "http://www.jb51.net/article/97488.htm",
        "title": "Node.js 数据加密传输浅析"
    },
    {
        "dir": "http://www.jb51.net/article/97391.htm",
        "title": "使用Node.js给图片加水印的方法"
    },
    {
        "dir": "http://www.jb51.net/article/97389.htm",
        "title": "Node.js批量给图片加水印的方法"
    },
    {
        "dir": "http://www.jb51.net/article/97372.htm",
        "title": "Windows系统下安装Node.js的步骤图文详解"
    },
    {
        "dir": "http://www.jb51.net/article/97232.htm",
        "title": "Node.js中路径处理模块path详解"
    },
    {
        "dir": "http://www.jb51.net/article/97202.htm",
        "title": "node.js缺少mysql模块运行报错的解决方法"
    },
    {
        "dir": "http://www.jb51.net/article/97113.htm",
        "title": "NodeJS中的MongoDB快速入门详细教程"
    },
    {
        "dir": "http://www.jb51.net/article/97086.htm",
        "title": "玩转NODE.JS（四）-搭建简单的聊天室的代码"
    },
    {
        "dir": "http://www.jb51.net/article/97034.htm",
        "title": "node+express制作爬虫教程"
    },
    {
        "dir": "http://www.jb51.net/article/96929.htm",
        "title": "Nodejs中解决cluster模块的多进程如何共享数据问题"
    },
    {
        "dir": "http://www.jb51.net/article/96911.htm",
        "title": "NodeJS整合银联网关支付（DEMO）"
    },
    {
        "dir": "http://www.jb51.net/article/96751.htm",
        "title": "nodejs的HTML分析利器node-jquery用法浅析"
    },
    {
        "dir": "http://www.jb51.net/article/96680.htm",
        "title": "NodeJS和BootStrap分页效果的实现代码"
    },
    {
        "dir": "http://www.jb51.net/article/96347.htm",
        "title": "Centos7 中安装 Node.js v4.4.4"
    },
    {
        "dir": "http://www.jb51.net/article/96309.htm",
        "title": "深入理解Node.js 事件循环和回调函数"
    },
    {
        "dir": "http://www.jb51.net/article/96303.htm",
        "title": "Centos7 中 Node.js安装简单方法"
    },
    {
        "dir": "http://www.jb51.net/article/95865.htm",
        "title": "node.js文件上传处理示例"
    },
    {
        "dir": "http://www.jb51.net/article/95841.htm",
        "title": "简单模拟node.js中require的加载机制"
    },
    {
        "dir": "http://www.jb51.net/article/95788.htm",
        "title": "NodeJS使用formidable实现文件上传"
    },
    {
        "dir": "http://www.jb51.net/article/95690.htm",
        "title": "利用python分析access日志的方法"
    },
    {
        "dir": "http://www.jb51.net/article/95641.htm",
        "title": "Node.js开启Https的实践详解"
    },
    {
        "dir": "http://www.jb51.net/article/95636.htm",
        "title": "利用yarn实现一个webpack+react种子"
    }
]